multicallable/__init__.py
multicallable/async_multicallable.py
multicallable/multicallable.py
multicallable/utils.py
multicallable/multicall/__init__.py
multicallable/multicall/async_multicall.py
multicallable/multicall/constants.py
multicallable/multicall/multicall.py
multicallable-7.2.1.dist-info/LICENCE
multicallable-7.2.1.dist-info/METADATA
multicallable-7.2.1.dist-info/WHEEL
multicallable-7.2.1.dist-info/top_level.txt
multicallable-7.2.1.dist-info/RECORD
