Metadata-Version: 2.1
Name: multicallable
Version: 7.2.1
Summary: Easy way to work with Multicall package
Home-page: https://github.com/deusfinance/multicallable
Author: MiKO, Naveed
Author-email: mikoronjoo@gmail.com, naveedinno@proton.me
Project-URL: Bug Tracker, https://github.com/deusfinance/multicallable/issues
Classifier: Programming Language :: Python :: 3
Classifier: License :: OSI Approved :: MIT License
Classifier: Operating System :: OS Independent
Requires-Python: <4.0.0,>=3.8.0
License-File: LICENCE
Requires-Dist: web3<8.0.0,>=7.0.0
